noteline/__init__.py
noteline/kf/__init__.py
noteline/kf/noteline_nb_op.py
noteline_kf-0.2.3.dist-info/LICENSE
noteline_kf-0.2.3.dist-info/METADATA
noteline_kf-0.2.3.dist-info/WHEEL
noteline_kf-0.2.3.dist-info/top_level.txt
noteline_kf-0.2.3.dist-info/RECORD
