Metadata-Version: 2.1
Name: noteline-kf
Version: 0.2.3
Summary: Noteline Kubeflow Pipeline step for executing Notebook
Home-page: https://github.com/noteline-org/noteline-kf
Author: Viacheslav Kovalevskyi
Author-email: viacheslav@kovalevskyi.com
License: UNKNOWN
Platform: UNKNOWN
Classifier: Programming Language :: Python :: 3
Classifier: License :: OSI Approved :: MIT License
Classifier: Operating System :: OS Independent
Requires-Python: >=3.6
Requires-Dist: kfp
Requires-Dist: noteline-sdk-core (>=2.2)
Requires-Dist: smart-open
